task1/rom.sv
module rom #(
    parameter   ADDRESS_WIDTH = 8,
                DATA_WIDTH = 8
)(
    input logic                         clk,
    input logic  [ADDRESS_WIDTH-1:0]    addr,
    output logic  [DATA_WIDTH-1:0]       dout
);

logic [DATA_WIDTH-1:0] rom_array [2**ADDRESS_WIDTH-1:0];

initial begin
        $display("Loading rom.");
        $readmemh("sinerom.mem", rom_array);
end;

always_ff @(posedge clk)
        //output is synchronous
        dout <= rom_array [addr];

endmodule

task1/counter.sv
module counter #(
    parameter WIDTH = 8
)(
    //interface signals 
    input logic             clk,      //clk
    input logic             rst,      //reset 
    input logic             en,       //counter enable
    input logic  [WIDTH-1:0] incr,    //increment to count by
    output logic [WIDTH-1:0] count   //count output
);

always_ff @ (posedge clk)
    if (rst) count <= {WIDTH{1'b0}};
    else     count <= en ? count + incr : count;

endmodule

task1/sinegen.sv
module sinegen #(
    parameter   A_WIDTH = 8,
                D_WIDTH = 8
)(
    // interface signals
    input   logic       clk,      //clk
    input   logic       rst,      //reset 
    input   logic       en,       //enable
    input   logic [D_WIDTH-1:0] incr,     //increment for addr counter
    output  logic [D_WIDTH-1:0] dout      // output data  
);

    logic [A_WIDTH-1:0]     address;  //interconnect wire

counter addrcounter(
    .clk (clk),
    .rst (rst),
    .en (en),
    .incr   (incr),
    .count (address)
);

rom sineROM (
    .clk (clk),
    .addr (address),
    .dout   (dout)
);

endmodule

task1/sinegen.vcd
$version Generated by VerilatedVcd $end
$date Wed Nov  2 18:48:40 2022 $end
$timescale 1ps $end

 $scope module TOP $end
  $var wire  1 # clk $end
  $var wire  8 ' dout [7:0] $end
  $var wire  1 % en $end
  $var wire  8 & incr [7:0] $end
  $var wire  1 $ rst $end
  $scope module sinegen $end
   $var wire 32 ) A_WIDTH [31:0] $end
   $var wire 32 ) D_WIDTH [31:0] $end
   $var wire  8 ( address [7:0] $end
   $var wire  1 # clk $end
   $var wire  8 ' dout [7:0] $end
   $var wire  1 % en $end
   $var wire  8 & incr [7:0] $end
   $var wire  1 $ rst $end
   $scope module addrcounter $end
    $var wire 32 ) WIDTH [31:0] $end
    $var wire  1 # clk $end
    $var wire  8 ( count [7:0] $end
    $var wire  1 % en $end
    $var wire  8 & incr [7:0] $end
    $var wire  1 $ rst $end
   $upscope $end
   $scope module sineROM $end
    $var wire 32 ) ADDRESS_WIDTH [31:0] $end
    $var wire 32 ) DATA_WIDTH [31:0] $end
    $var wire  8 ( addr [7:0] $end
    $var wire  1 # clk $end
    $var wire  8 ' dout [7:0] $end
   $upscope $end
  $upscope $end
 $upscope $end
$enddefinitions $end


#0
0#
1$
1%
b00000001 &
b00000000 '
b00000000 (
b00000000000000000000000000001000 )
#1
1#
#2
0#
#3
1#
b11111110 '
#4
0#
0$
#5
1#
b00000001 (
#6
0#
#7
1#
b11111101 '
b00000010 (
#8
0#
#9
1#
b00000011 (
#10
0#
#11
1#
b00000100 (
#12
0#
#13
1#
b00000101 (
#14
0#
#15
1#
b00000110 (
#16
0#
#17
1#
b11111100 '
b00000111 (
#18
0#
#19
1#
b00001000 (
#20
0#
#21
1#
b11111011 '
b00001001 (
#22
0#
#23
1#
b11111010 '
b00001010 (
#24
0#
#25
1#
b00001011 (
#26
0#
#27
1#
b11111001 '
b00001100 (
#28
0#
#29
1#
b11111000 '
b00001101 (
#30
0#
#31
1#
b11110111 '
b00001110 (
#32
0#
#33
1#
b11110110 '
b00001111 (
#34
0#
#35
1#
b11110101 '
b00010000 (
#36
0#
#37
1#
b11110100 '
b00010001 (
#38
0#
#39
1#
b11110011 '
b00010010 (
#40
0#
#41
1#
b11110001 '
b00010011 (
#42
0#
#43
1#
b11110000 '
b00010100 (
#44
0#
#45
1#
b11101111 '
b00010101 (
#46
0#
#47
1#
b11101101 '
b00010110 (
#48
0#
#49
1#
b11101011 '
b00010111 (
#50
0#
#51
1#
b11101010 '
b00011000 (
#52
0#
#53
1#
b11101000 '
b00011001 (
#54
0#
#55
1#
b11100110 '
b00011010 (
#56
0#
#57
1#
b11100101 '
b00011011 (
#58
0#
#59
1#
b11100011 '
b00011100 (
#60
0#
#61
1#
b11100001 '
b00011101 (
#62
0#
#63
1#
b11011111 '
b00011110 (
#64
0#
#65
1#
b11011101 '
b00011111 (
#66
0#
#67
1#
b11011010 '
b00100000 (
#68
0#
#69
1#
b11011000 '
b00100001 (
#70
0#
#71
1#
b11010110 '
b00100010 (
#72
0#
#73
1#
b11010100 '
b00100011 (
#74
0#
#75
1#
b11010001 '
b00100100 (
#76
0#
#77
1#
b11001111 '
b00100101 (
#78
0#
#79
1#
b11001101 '
b00100110 (
#80
0#
#81
1#
b11001010 '
b00100111 (
#82
0#
#83
1#
b11001000 '
b00101000 (
#84
0#
#85
1#
b11000101 '
b00101001 (
#86
0#
#87
1#
b11000010 '
b00101010 (
#88
0#
#89
1#
b11000000 '
b00101011 (
#90
0#
#91
1#
b10111101 '
b00101100 (
#92
0#
#93
1#
b10111010 '
b00101101 (
#94
0#
#95
1#
b10111000 '
b00101110 (
#96
0#
#97
1#
b10110101 '
b00101111 (
#98
0#
#99
1#
b10110010 '
b00110000 (
#100
0#
#101
1#
b10101111 '
b00110001 (
#102
0#
#103
1#
b10101100 '
b00110010 (
#104
0#
#105
1#
b10101001 '
b00110011 (
#106
0#
#107
1#
b10100110 '
b00110100 (
#108
0#
#109
1#
b10100011 '
b00110101 (
#110
0#
#111
1#
b10100000 '
b00110110 (
#112
0#
#113
1#
b10011101 '
b00110111 (
#114
0#
#115
1#
b10011010 '
b00111000 (
#116
0#
#117
1#
b10010111 '
b00111001 (
#118
0#
#119
1#
b10010100 '
b00111010 (
#120
0#
#121
1#
b10010001 '
b00111011 (
#122
0#
#123
1#
b10001110 '
b00111100 (
#124
0#
#125
1#
b10001011 '
b00111101 (
#126
0#
#127
1#
b10001000 '
b00111110 (
#128
0#
#129
1#
b10000101 '
b00111111 (
#130
0#
#131
1#
b10000010 '
b01000000 (
#132
0#
#133
1#
b01111110 '
b01000001 (
#134
0#
#135
1#
b01111011 '
b01000010 (
#136
0#
#137
1#
b01111000 '
b01000011 (
#138
0#
#139
1#
b01110101 '
b01000100 (
#140
0#
#141
1#
b01110010 '
b01000101 (
#142
0#
#143
1#
b01101111 '
b01000110 (
#144
0#
#145
1#
b01101100 '
b01000111 (
#146
0#
#147
1#
b01101001 '
b01001000 (
#148
0#
#149
1#
b01100110 '
b01001001 (
#150
0#
#151
1#
b01100011 '
b01001010 (
#152
0#
#153
1#
b01100000 '
b01001011 (
#154
0#
#155
1#
b01011101 '
b01001100 (
#156
0#
#157
1#
b01011010 '
b01001101 (
#158
0#
#159
1#
b01010111 '
b01001110 (
#160
0#
#161
1#
b01010100 '
b01001111 (
#162
0#
#163
1#
b01010001 '
b01010000 (
#164
0#
#165
1#
b01001110 '
b01010001 (
#166
0#
#167
1#
b01001011 '
b01010010 (
#168
0#
#169
1#
b01001000 '
b01010011 (
#170
0#
#171
1#
b01000101 '
b01010100 (
#172
0#
#173
1#
b01000011 '
b01010101 (
#174
0#
#175
1#
b01000000 '
b01010110 (
#176
0#
#177
1#
b00111101 '
b01010111 (
#178
0#
#179
1#
b00111011 '
b01011000 (
#180
0#
#181
1#
b00111000 '
b01011001 (
#182
0#
#183
1#
b00110101 '
b01011010 (
#184
0#
#185
1#
b00110011 '
b01011011 (
#186
0#
#187
1#
b00110000 '
b01011100 (
#188
0#
#189
1#
b00101110 '
b01011101 (
#190
0#
#191
1#
b00101100 '
b01011110 (
#192
0#
#193
1#
b00101001 '
b01011111 (
#194
0#
#195
1#
b00100111 '
b01100000 (
#196
0#
#197
1#
b00100101 '
b01100001 (
#198
0#
#199
1#
b00100011 '
b01100010 (
#200
0#
#201
1#
b00100000 '
b01100011 (
#202
0#
#203
1#
b00011110 '
b01100100 (
#204
0#
#205
1#
b00011100 '
b01100101 (
#206
0#
#207
1#
b00011010 '
b01100110 (
#208
0#
#209
1#
b00011000 '
b01100111 (
#210
0#
#211
1#
b00010111 '
b01101000 (
#212
0#
#213
1#
b00010101 '
b01101001 (
#214
0#
#215
1#
b00010011 '
b01101010 (
#216
0#
#217
1#
b00010010 '
b01101011 (
#218
0#
#219
1#
b00010000 '
b01101100 (
#220
0#
#221
1#
b00001110 '
b01101101 (
#222
0#
#223
1#
b00001101 '
b01101110 (
#224
0#
#225
1#
b00001100 '
b01101111 (
#226
0#
#227
1#
b00001010 '
b01110000 (
#228
0#
#229
1#
b00001001 '
b01110001 (
#230
0#
#231
1#
b00001000 '
b01110010 (
#232
0#
#233
1#
b00000111 '
b01110011 (
#234
0#
#235
1#
b00000110 '
b01110100 (
#236
0#
#237
1#
b00000101 '
b01110101 (
#238
0#
#239
1#
b00000100 '
b01110110 (
#240
0#
#241
1#
b00000011 '
b01110111 (
#242
0#
#243
1#
b01111000 (
#244
0#
#245
1#
b00000010 '
b01111001 (
#246
0#
#247
1#
b00000001 '
b01111010 (
#248
0#
#249
1#
b01111011 (
#250
0#
#251
1#
b00000000 '
b01111100 (
#252
0#
#253
1#
b01111101 (
#254
0#
#255
1#
b01111110 (
#256
0#
#257
1#
b01111111 (
#258
0#
#259
1#
b10000000 (
#260
0#
#261
1#
b10000001 (
#262
0#
#263
1#
b10000010 (
#264
0#
#265
1#
b10000011 (
#266
0#
#267
1#
b10000100 (
#268
0#
#269
1#
b10000101 (
#270
0#
#271
1#
b10000110 (
#272
0#
#273
1#
b00000001 '
b10000111 (
#274
0#
#275
1#
b10001000 (
#276
0#
#277
1#
b00000010 '
b10001001 (
#278
0#
#279
1#
b00000011 '
b10001010 (
#280
0#
#281
1#
b10001011 (
#282
0#
#283
1#
b00000100 '
b10001100 (
#284
0#
#285
1#
b00000101 '
b10001101 (
#286
0#
#287
1#
b00000110 '
b10001110 (
#288
0#
#289
1#
b00000111 '
b10001111 (
#290
0#
#291
1#
b00001000 '
b10010000 (
#292
0#
#293
1#
b00001001 '
b10010001 (
#294
0#
#295
1#
b00001010 '
b10010010 (
#296
0#
#297
1#
b00001100 '
b10010011 (
#298
0#
#299
1#
b00001101 '
b10010100 (
#300
0#
#301
1#
b00001110 '
b10010101 (
#302
0#
#303
1#
b00010000 '
b10010110 (
#304
0#
#305
1#
b00010010 '
b10010111 (
#306
0#
#307
1#
b00010011 '
b10011000 (
#308
0#
#309
1#
b00010101 '
b10011001 (
#310
0#
#311
1#
b00010111 '
b10011010 (
#312
0#
#313
1#
b00011000 '
b10011011 (
#314
0#
#315
1#
b00011010 '
b10011100 (
#316
0#
#317
1#
b00011100 '
b10011101 (
#318
0#
#319
1#
b00011110 '
b10011110 (
#320
0#
#321
1#
b00100000 '
b10011111 (
#322
0#
#323
1#
b00100011 '
b10100000 (
#324
0#
#325
1#
b00100101 '
b10100001 (
#326
0#
#327
1#
b00100111 '
b10100010 (
#328
0#
#329
1#
b00101001 '
b10100011 (
#330
0#
#331
1#
b00101100 '
b10100100 (
#332
0#
#333
1#
b00101110 '
b10100101 (
#334
0#
#335
1#
b00110000 '
b10100110 (
#336
0#
#337
1#
b00110011 '
b10100111 (
#338
0#
#339
1#
b00110101 '
b10101000 (
#340
0#
#341
1#
b00111000 '
b10101001 (
#342
0#
#343
1#
b00111011 '
b10101010 (
#344
0#
#345
1#
b00111101 '
b10101011 (
#346
0#
#347
1#
b01000000 '
b10101100 (
#348
0#
#349
1#
b01000011 '
b10101101 (
#350
0#
#351
1#
b01000101 '
b10101110 (
#352
0#
#353
1#
b01001000 '
b10101111 (
#354
0#
#355
1#
b01001011 '
b10110000 (
#356
0#
#357
1#
b01001110 '
b10110001 (
#358
0#
#359
1#
b01010001 '
b10110010 (
#360
0#
#361
1#
b01010100 '
b10110011 (
#362
0#
#363
1#
b01010111 '
b10110100 (
#364
0#
#365
1#
b01011010 '
b10110101 (
#366
0#
#367
1#
b01011101 '
b10110110 (
#368
0#
#369
1#
b01100000 '
b10110111 (
#370
0#
#371
1#
b01100011 '
b10111000 (
#372
0#
#373
1#
b01100110 '
b10111001 (
#374
0#
#375
1#
b01101001 '
b10111010 (
#376
0#
#377
1#
b01101100 '
b10111011 (
#378
0#
#379
1#
b01101111 '
b10111100 (
#380
0#
#381
1#
b01110010 '
b10111101 (
#382
0#
#383
1#
b01110101 '
b10111110 (
#384
0#
#385
1#
b01111000 '
b10111111 (
#386
0#
#387
1#
b01111011 '
b11000000 (
#388
0#
#389
1#
b01111111 '
b11000001 (
#390
0#
#391
1#
b10000010 '
b11000010 (
#392
0#
#393
1#
b10000101 '
b11000011 (
#394
0#
#395
1#
b10001000 '
b11000100 (
#396
0#
#397
1#
b10001011 '
b11000101 (
#398
0#
#399
1#
b10001110 '
b11000110 (
#400
0#
#401
1#
b10010001 '
b11000111 (
#402
0#
#403
1#
b10010100 '
b11001000 (
#404
0#
#405
1#
b10010111 '
b11001001 (
#406
0#
#407
1#
b10011010 '
b11001010 (
#408
0#
#409
1#
b10011101 '
b11001011 (
#410
0#
#411
1#
b10100000 '
b11001100 (
#412
0#
#413
1#
b10100011 '
b11001101 (
#414
0#
#415
1#
b10100110 '
b11001110 (
#416
0#
#417
1#
b10101001 '
b11001111 (
#418
0#
#419
1#
b10101100 '
b11010000 (
#420
0#
#421
1#
b10101111 '
b11010001 (
#422
0#
#423
1#
b10110010 '
b11010010 (
#424
0#
#425
1#
b10110101 '
b11010011 (
#426
0#
#427
1#
b10111000 '
b11010100 (
#428
0#
#429
1#
b10111010 '
b11010101 (
#430
0#
#431
1#
b10111101 '
b11010110 (
#432
0#
#433
1#
b11000000 '
b11010111 (
#434
0#
#435
1#
b11000010 '
b11011000 (
#436
0#
#437
1#
b11000101 '
b11011001 (
#438
0#
#439
1#
b11001000 '
b11011010 (
#440
0#
#441
1#
b11001010 '
b11011011 (
#442
0#
#443
1#
b11001101 '
b11011100 (
#444
0#
#445
1#
b11001111 '
b11011101 (
#446
0#
#447
1#
b11010001 '
b11011110 (
#448
0#
#449
1#
b11010100 '
b11011111 (
#450
0#
#451
1#
b11010110 '
b11100000 (
#452
0#
#453
1#
b11011000 '
b11100001 (
#454
0#
#455
1#
b11011010 '
b11100010 (
#456
0#
#457
1#
b11011101 '
b11100011 (
#458
0#
#459
1#
b11011111 '
b11100100 (
#460
0#
#461
1#
b11100001 '
b11100101 (
#462
0#
#463
1#
b11100011 '
b11100110 (
#464
0#
#465
1#
b11100101 '
b11100111 (
#466
0#
#467
1#
b11100110 '
b11101000 (
#468
0#
#469
1#
b11101000 '
b11101001 (
#470
0#
#471
1#
b11101010 '
b11101010 (
#472
0#
#473
1#
b11101011 '
b11101011 (
#474
0#
#475
1#
b11101101 '
b11101100 (
#476
0#
#477
1#
b11101111 '
b11101101 (
#478
0#
#479
1#
b11110000 '
b11101110 (
#480
0#
#481
1#
b11110001 '
b11101111 (
#482
0#
#483
1#
b11110011 '
b11110000 (
#484
0#
#485
1#
b11110100 '
b11110001 (
#486
0#
#487
1#
b11110101 '
b11110010 (
#488
0#
#489
1#
b11110110 '
b11110011 (
#490
0#
#491
1#
b11110111 '
b11110100 (
#492
0#
#493
1#
b11111000 '
b11110101 (
#494
0#
#495
1#
b11111001 '
b11110110 (
#496
0#
#497
1#
b11111010 '
b11110111 (
#498
0#
#499
1#
b11111000 (
#500
0#
#501
1#
b11111011 '
b11111001 (
#502
0#
#503
1#
b11111100 '
b11111010 (
#504
0#
#505
1#
b11111011 (
#506
0#
#507
1#
b11111101 '
b11111100 (
#508
0#
#509
1#
b11111101 (
#510
0#
#511
1#
b11111110 (
#512
0#
#513
1#
b11111111 (
#514
0#
#515
1#
b00000000 (
#516
0#
#517
1#
b11111110 '
b00000001 (
#518
0#
#519
1#
b11111101 '
b00000010 (
#520
0#
#521
1#
b00000011 (
#522
0#
#523
1#
b00000100 (
#524
0#
#525
1#
b00000101 (
#526
0#
#527
1#
b00000110 (
#528
0#
#529
1#
b11111100 '
b00000111 (
#530
0#
#531
1#
b00001000 (
#532
0#
#533
1#
b11111011 '
b00001001 (
#534
0#
#535
1#
b11111010 '
b00001010 (
#536
0#
#537
1#
b00001011 (
#538
0#
#539
1#
b11111001 '
b00001100 (
#540
0#
#541
1#
b11111000 '
b00001101 (
#542
0#
#543
1#
b11110111 '
b00001110 (
#544
0#
#545
1#
b11110110 '
b00001111 (
#546
0#
#547
1#
b11110101 '
b00010000 (
#548
0#
#549
1#
b11110100 '
b00010001 (
#550
0#
#551
1#
b11110011 '
b00010010 (
#552
0#
#553
1#
b11110001 '
b00010011 (
#554
0#
#555
1#
b11110000 '
b00010100 (
#556
0#
#557
1#
b11101111 '
b00010101 (
#558
0#
#559
1#
b11101101 '
b00010110 (
#560
0#
#561
1#
b11101011 '
b00010111 (
#562
0#
#563
1#
b11101010 '
b00011000 (
#564
0#
#565
1#
b11101000 '
b00011001 (
#566
0#
#567
1#
b11100110 '
b00011010 (
#568
0#
#569
1#
b11100101 '
b00011011 (
#570
0#
#571
1#
b11100011 '
b00011100 (
#572
0#
#573
1#
b11100001 '
b00011101 (
#574
0#
#575
1#
b11011111 '
b00011110 (
#576
0#
#577
1#
b11011101 '
b00011111 (
#578
0#
#579
1#
b11011010 '
b00100000 (
#580
0#
#581
1#
b11011000 '
b00100001 (
#582
0#
#583
1#
b11010110 '
b00100010 (
#584
0#
#585
1#
b11010100 '
b00100011 (
#586
0#
#587
1#
b11010001 '
b00100100 (
#588
0#
#589
1#
b11001111 '
b00100101 (
#590
0#
#591
1#
b11001101 '
b00100110 (
#592
0#
#593
1#
b11001010 '
b00100111 (
#594
0#
#595
1#
b11001000 '
b00101000 (
#596
0#
#597
1#
b11000101 '
b00101001 (
#598
0#
#599
1#
b11000010 '
b00101010 (
#600
0#
#601
1#
b11000000 '
b00101011 (
#602
0#
#603
1#
b10111101 '
b00101100 (
#604
0#
#605
1#
b10111010 '
b00101101 (
#606
0#
#607
1#
b10111000 '
b00101110 (
#608
0#
#609
1#
b10110101 '
b00101111 (
#610
0#
#611
1#
b10110010 '
b00110000 (
#612
0#
#613
1#
b10101111 '
b00110001 (
#614
0#
#615
1#
b10101100 '
b00110010 (
#616
0#
#617
1#
b10101001 '
b00110011 (
#618
0#
#619
1#
b10100110 '
b00110100 (
#620
0#
#621
1#
b10100011 '
b00110101 (
#622
0#
#623
1#
b10100000 '
b00110110 (
#624
0#
#625
1#
b10011101 '
b00110111 (
#626
0#
#627
1#
b10011010 '
b00111000 (
#628
0#
#629
1#
b10010111 '
b00111001 (
#630
0#
#631
1#
b10010100 '
b00111010 (
#632
0#
#633
1#
b10010001 '
b00111011 (
#634
0#
#635
1#
b10001110 '
b00111100 (
#636
0#
#637
1#
b10001011 '
b00111101 (
#638
0#
#639
1#
b10001000 '
b00111110 (
#640
0#
#641
1#
b10000101 '
b00111111 (
#642
0#
#643
1#
b10000010 '
b01000000 (
#644
0#
#645
1#
b01111110 '
b01000001 (
#646
0#
#647
1#
b01111011 '
b01000010 (
#648
0#
#649
1#
b01111000 '
b01000011 (
#650
0#
#651
1#
b01110101 '
b01000100 (
#652
0#
#653
1#
b01110010 '
b01000101 (
#654
0#
#655
1#
b01101111 '
b01000110 (
#656
0#
#657
1#
b01101100 '
b01000111 (
#658
0#
#659
1#
b01101001 '
b01001000 (
#660
0#
#661
1#
b01100110 '
b01001001 (
#662
0#
#663
1#
b01100011 '
b01001010 (
#664
0#
#665
1#
b01100000 '
b01001011 (
#666
0#
#667
1#
b01011101 '
b01001100 (
#668
0#
#669
1#
b01011010 '
b01001101 (
#670
0#
#671
1#
b01010111 '
b01001110 (
#672
0#
#673
1#
b01010100 '
b01001111 (
#674
0#
#675
1#
b01010001 '
b01010000 (
#676
0#
#677
1#
b01001110 '
b01010001 (
#678
0#
#679
1#
b01001011 '
b01010010 (
#680
0#
#681
1#
b01001000 '
b01010011 (
#682
0#
#683
1#
b01000101 '
b01010100 (
#684
0#
#685
1#
b01000011 '
b01010101 (
#686
0#
#687
1#
b01000000 '
b01010110 (
#688
0#
#689
1#
b00111101 '
b01010111 (
#690
0#
#691
1#
b00111011 '
b01011000 (
#692
0#
#693
1#
b00111000 '
b01011001 (
#694
0#
#695
1#
b00110101 '
b01011010 (
#696
0#
#697
1#
b00110011 '
b01011011 (
#698
0#
#699
1#
b00110000 '
b01011100 (
#700
0#
#701
1#
b00101110 '
b01011101 (
#702
0#
#703
1#
b00101100 '
b01011110 (
#704
0#
#705
1#
b00101001 '
b01011111 (
#706
0#
#707
1#
b00100111 '
b01100000 (
#708
0#
#709
1#
b00100101 '
b01100001 (
#710
0#
#711
1#
b00100011 '
b01100010 (
#712
0#
#713
1#
b00100000 '
b01100011 (
#714
0#
#715
1#
b00011110 '
b01100100 (
#716
0#
#717
1#
b00011100 '
b01100101 (
#718
0#
#719
1#
b00011010 '
b01100110 (
#720
0#
#721
1#
b00011000 '
b01100111 (
#722
0#
#723
1#
b00010111 '
b01101000 (
#724
0#
#725
1#
b00010101 '
b01101001 (
#726
0#
#727
1#
b00010011 '
b01101010 (
#728
0#
#729
1#
b00010010 '
b01101011 (
#730
0#
#731
1#
b00010000 '
b01101100 (
#732
0#
#733
1#
b00001110 '
b01101101 (
#734
0#
#735
1#
b00001101 '
b01101110 (
#736
0#
#737
1#
b00001100 '
b01101111 (
#738
0#
#739
1#
b00001010 '
b01110000 (
#740
0#
#741
1#
b00001001 '
b01110001 (
#742
0#
#743
1#
b00001000 '
b01110010 (
#744
0#
#745
1#
b00000111 '
b01110011 (
#746
0#
#747
1#
b00000110 '
b01110100 (
#748
0#
#749
1#
b00000101 '
b01110101 (
#750
0#
#751
1#
b00000100 '
b01110110 (
#752
0#
#753
1#
b00000011 '
b01110111 (
#754
0#
#755
1#
b01111000 (
#756
0#
#757
1#
b00000010 '
b01111001 (
#758
0#
#759
1#
b00000001 '
b01111010 (
#760
0#
#761
1#
b01111011 (
#762
0#
#763
1#
b00000000 '
b01111100 (
#764
0#
#765
1#
b01111101 (
#766
0#
#767
1#
b01111110 (
#768
0#
#769
1#
b01111111 (
#770
0#
#771
1#
b10000000 (
#772
0#
#773
1#
b10000001 (
#774
0#
#775
1#
b10000010 (
#776
0#
#777
1#
b10000011 (
#778
0#
#779
1#
b10000100 (
#780
0#
#781
1#
b10000101 (
#782
0#
#783
1#
b10000110 (
#784
0#
#785
1#
b00000001 '
b10000111 (
#786
0#
#787
1#
b10001000 (
#788
0#
#789
1#
b00000010 '
b10001001 (
#790
0#
#791
1#
b00000011 '
b10001010 (
#792
0#
#793
1#
b10001011 (
#794
0#
#795
1#
b00000100 '
b10001100 (
#796
0#
#797
1#
b00000101 '
b10001101 (
#798
0#
#799
1#
b00000110 '
b10001110 (
#800
0#
#801
1#
b00000111 '
b10001111 (
#802
0#
#803
1#
b00001000 '
b10010000 (
#804
0#
#805
1#
b00001001 '
b10010001 (
#806
0#
#807
1#
b00001010 '
b10010010 (
#808
0#
#809
1#
b00001100 '
b10010011 (
#810
0#
#811
1#
b00001101 '
b10010100 (
#812
0#
#813
1#
b00001110 '
b10010101 (
#814
0#
#815
1#
b00010000 '
b10010110 (
#816
0#
#817
1#
b00010010 '
b10010111 (
#818
0#
#819
1#
b00010011 '
b10011000 (
#820
0#
#821
1#
b00010101 '
b10011001 (
#822
0#
#823
1#
b00010111 '
b10011010 (
#824
0#
#825
1#
b00011000 '
b10011011 (
#826
0#
#827
1#
b00011010 '
b10011100 (
#828
0#
#829
1#
b00011100 '
b10011101 (
#830
0#
#831
1#
b00011110 '
b10011110 (
#832
0#
#833
1#
b00100000 '
b10011111 (
#834
0#
#835
1#
b00100011 '
b10100000 (
#836
0#
#837
1#
b00100101 '
b10100001 (
#838
0#
#839
1#
b00100111 '
b10100010 (
#840
0#
#841
1#
b00101001 '
b10100011 (
#842
0#
#843
1#
b00101100 '
b10100100 (
#844
0#
#845
1#
b00101110 '
b10100101 (
#846
0#
#847
1#
b00110000 '
b10100110 (
#848
0#
#849
1#
b00110011 '
b10100111 (
#850
0#
#851
1#
b00110101 '
b10101000 (
#852
0#
#853
1#
b00111000 '
b10101001 (
#854
0#
#855
1#
b00111011 '
b10101010 (
#856
0#
#857
1#
b00111101 '
b10101011 (
#858
0#
#859
1#
b01000000 '
b10101100 (
#860
0#
#861
1#
b01000011 '
b10101101 (
#862
0#
#863
1#
b01000101 '
b10101110 (
#864
0#
#865
1#
b01001000 '
b10101111 (
#866
0#
#867
1#
b01001011 '
b10110000 (
#868
0#
#869
1#
b01001110 '
b10110001 (
#870
0#
#871
1#
b01010001 '
b10110010 (
#872
0#
#873
1#
b01010100 '
b10110011 (
#874
0#
#875
1#
b01010111 '
b10110100 (
#876
0#
#877
1#
b01011010 '
b10110101 (
#878
0#
#879
1#
b01011101 '
b10110110 (
#880
0#
#881
1#
b01100000 '
b10110111 (
#882
0#
#883
1#
b01100011 '
b10111000 (
#884
0#
#885
1#
b01100110 '
b10111001 (
#886
0#
#887
1#
b01101001 '
b10111010 (
#888
0#
#889
1#
b01101100 '
b10111011 (
#890
0#
#891
1#
b01101111 '
b10111100 (
#892
0#
#893
1#
b01110010 '
b10111101 (
#894
0#
#895
1#
b01110101 '
b10111110 (
#896
0#
#897
1#
b01111000 '
b10111111 (
#898
0#
#899
1#
b01111011 '
b11000000 (
#900
0#
#901
1#
b01111111 '
b11000001 (
#902
0#
#903
1#
b10000010 '
b11000010 (
#904
0#
#905
1#
b10000101 '
b11000011 (
#906
0#
#907
1#
b10001000 '
b11000100 (
#908
0#
#909
1#
b10001011 '
b11000101 (
#910
0#
#911
1#
b10001110 '
b11000110 (
#912
0#
#913
1#
b10010001 '
b11000111 (
#914
0#
#915
1#
b10010100 '
b11001000 (
#916
0#
#917
1#
b10010111 '
b11001001 (
#918
0#
#919
1#
b10011010 '
b11001010 (
#920
0#
#921
1#
b10011101 '
b11001011 (
#922
0#
#923
1#
b10100000 '
b11001100 (
#924
0#
#925
1#
b10100011 '
b11001101 (
#926
0#
#927
1#
b10100110 '
b11001110 (
#928
0#
#929
1#
b10101001 '
b11001111 (
#930
0#
#931
1#
b10101100 '
b11010000 (
#932
0#
#933
1#
b10101111 '
b11010001 (
#934
0#
#935
1#
b10110010 '
b11010010 (
#936
0#
#937
1#
b10110101 '
b11010011 (
#938
0#
#939
1#
b10111000 '
b11010100 (
#940
0#
#941
1#
b10111010 '
b11010101 (
#942
0#
#943
1#
b10111101 '
b11010110 (
#944
0#
#945
1#
b11000000 '
b11010111 (
#946
0#
#947
1#
b11000010 '
b11011000 (
#948
0#
#949
1#
b11000101 '
b11011001 (
#950
0#
#951
1#
b11001000 '
b11011010 (
#952
0#
#953
1#
b11001010 '
b11011011 (
#954
0#
#955
1#
b11001101 '
b11011100 (
#956
0#
#957
1#
b11001111 '
b11011101 (
#958
0#
#959
1#
b11010001 '
b11011110 (
#960
0#
#961
1#
b11010100 '
b11011111 (
#962
0#
#963
1#
b11010110 '
b11100000 (
#964
0#
#965
1#
b11011000 '
b11100001 (
#966
0#
#967
1#
b11011010 '
b11100010 (
#968
0#
#969
1#
b11011101 '
b11100011 (
#970
0#
#971
1#
b11011111 '
b11100100 (
#972
0#
#973
1#
b11100001 '
b11100101 (
#974
0#
#975
1#
b11100011 '
b11100110 (
#976
0#
#977
1#
b11100101 '
b11100111 (
#978
0#
#979
1#
b11100110 '
b11101000 (
#980
0#
#981
1#
b11101000 '
b11101001 (
#982
0#
#983
1#
b11101010 '
b11101010 (
#984
0#
#985
1#
b11101011 '
b11101011 (
#986
0#
#987
1#
b11101101 '
b11101100 (
#988
0#
#989
1#
b11101111 '
b11101101 (
#990
0#
#991
1#
b11110000 '
b11101110 (
#992
0#
#993
1#
b11110001 '
b11101111 (
#994
0#
#995
1#
b11110011 '
b11110000 (
#996
0#
#997
1#
b11110100 '
b11110001 (
#998
0#
#999
1#
b11110101 '
b11110010 (
#1000
0#
#1001
1#
b11110110 '
b11110011 (
#1002
0#
#1003
1#
b11110111 '
b11110100 (
#1004
0#
#1005
1#
b11111000 '
b11110101 (
#1006
0#
#1007
1#
b11111001 '
b11110110 (
#1008
0#
#1009
1#
b11111010 '
b11110111 (
#1010
0#
#1011
1#
b11111000 (
#1012
0#
#1013
1#
b11111011 '
b11111001 (
#1014
0#
#1015
1#
b11111100 '
b11111010 (
#1016
0#
#1017
1#
b11111011 (
#1018
0#
#1019
1#
b11111101 '
b11111100 (
#1020
0#
#1021
1#
b11111101 (
#1022
0#
#1023
1#
b11111110 (
#1024
0#
#1025
1#
b11111111 (
#1026
0#
#1027
1#
b00000000 (
#1028
0#
#1029
1#
b11111110 '
b00000001 (
#1030
0#
#1031
1#
b11111101 '
b00000010 (
#1032
0#
#1033
1#
b00000011 (
#1034
0#
#1035
1#
b00000100 (
#1036
0#
#1037
1#
b00000101 (
#1038
0#
#1039
1#
b00000110 (
#1040
0#
#1041
1#
b11111100 '
b00000111 (
#1042
0#
#1043
1#
b00001000 (
#1044
0#
#1045
1#
b11111011 '
b00001001 (
#1046
0#
#1047
1#
b11111010 '
b00001010 (
#1048
0#
#1049
1#
b00001011 (
#1050
0#
#1051
1#
b11111001 '
b00001100 (
#1052
0#
#1053
1#
b11111000 '
b00001101 (
#1054
0#
#1055
1#
b11110111 '
b00001110 (
#1056
0#
#1057
1#
b11110110 '
b00001111 (
#1058
0#
#1059
1#
b11110101 '
b00010000 (
#1060
0#
#1061
1#
b11110100 '
b00010001 (
#1062
0#
#1063
1#
b11110011 '
b00010010 (
#1064
0#
#1065
1#
b11110001 '
b00010011 (
#1066
0#
#1067
1#
b11110000 '
b00010100 (
#1068
0#
#1069
1#
b11101111 '
b00010101 (
#1070
0#
#1071
1#
b11101101 '
b00010110 (
#1072
0#
#1073
1#
b11101011 '
b00010111 (
#1074
0#
#1075
1#
b11101010 '
b00011000 (
#1076
0#
